{
  "Aluguel de imóveis para escritório político":17496630.31,
  "Aquisição de material de consumo":3225664.65,
  "Locomoção, hospedagem, alimentação, combustíveis e":20366699.28,
  "Divulgação da atividade parlamentar":11906742.78,
  "Passagens aéreas, aquáticas e terrestres nacionais":22987407.41,
  "Diárias":2036159.47,
  "Combustíveis":1610725.43,
  "Outros materiais":1356784.87,
  "Correios":10615344.12,
  "Contratação de serviços de apoio ao parlamentar":12489596.97,
  "Ressarcimento de Passagens":1062626.55,
  "Serviços de Segurança Privada":1507594.13
}