{
  "Aluguel de imóveis para escritório político":17812046.6,
  "Aquisição de material de consumo":3289533.63,
  "Locomoção, hospedagem, alimentação, combustíveis e":20678219.15,
  "Divulgação da atividade parlamentar":11943737.19,
  "Passagens aéreas, aquáticas e terrestres nacionais":23327359.87,
  "Diárias":2036159.47,
  "Combustíveis":1610725.43,
  "Outros materiais":1386620.57,
  "Correios":10669054.37,
  "Contratação de serviços de apoio ao parlamentar":12709064.69,
  "Ressarcimento de Passagens":1062626.55,
  "Serviços de Segurança Privada":1511941.24
}