{
  "Aluguel de imóveis para escritório político":17314879.45,
  "Aquisição de material de consumo":3188924.68,
  "Locomoção, hospedagem, alimentação, combustíveis e":20239984.04,
  "Divulgação da atividade parlamentar":11872242.78,
  "Passagens aéreas, aquáticas e terrestres nacionais":22781711.09,
  "Diárias":2036159.47,
  "Combustíveis":1610725.43,
  "Outros materiais":1331340.75,
  "Correios":10552006.0,
  "Contratação de serviços de apoio ao parlamentar":12363324.95,
  "Ressarcimento de Passagens":1062626.55,
  "Serviços de Segurança Privada":1507519.13
}